django_valkey/__init__.py
django_valkey/base.py
django_valkey/base_client.py
django_valkey/base_pool.py
django_valkey/cache.py
django_valkey/exceptions.py
django_valkey/hash_ring.py
django_valkey/pool.py
django_valkey/util.py
django_valkey/async_cache/__init__.py
django_valkey/async_cache/cache.py
django_valkey/async_cache/pool.py
django_valkey/async_cache/client/__init__.py
django_valkey/async_cache/client/default.py
django_valkey/async_cache/client/herd.py
django_valkey/async_cache/client/sentinel.py
django_valkey/client/__init__.py
django_valkey/client/default.py
django_valkey/client/herd.py
django_valkey/client/sentinel.py
django_valkey/client/sharded.py
django_valkey/cluster_cache/__init__.py
django_valkey/cluster_cache/cache.py
django_valkey/cluster_cache/pool.py
django_valkey/cluster_cache/client/__init__.py
django_valkey/cluster_cache/client/default.py
django_valkey/compressors/__init__.py
django_valkey/compressors/base.py
django_valkey/compressors/brotli.py
django_valkey/compressors/bz2.py
django_valkey/compressors/gzip.py
django_valkey/compressors/identity.py
django_valkey/compressors/lz4.py
django_valkey/compressors/lzma.py
django_valkey/compressors/zlib.py
django_valkey/compressors/zstd.py
django_valkey/serializers/__init__.py
django_valkey/serializers/base.py
django_valkey/serializers/json.py
django_valkey/serializers/msgpack.py
django_valkey/serializers/msgspec.py
django_valkey/serializers/pickle.py
django_valkey-0.4.0.dist-info/METADATA
django_valkey-0.4.0.dist-info/WHEEL
django_valkey-0.4.0.dist-info/licenses/AUTHORS.rst
django_valkey-0.4.0.dist-info/licenses/LICENSE
django_valkey-0.4.0.dist-info/RECORD
