Metadata-Version: 2.4
Name: django-valkey
Version: 0.4.0
Summary: a valkey backend for django
Project-URL: Homepage, https://github.com/django-commons/django-valkey
Project-URL: Source, https://github.com/django-commons/django-valkey
Project-URL: Issues, https://github.com/django-commons/django-valkey/issues
Project-URL: Documentation, https://django-valkey.readthedocs.io/en/latest/
Maintainer-email: amirreza <amir.rsf1380@gmail.com>
License-Expression: BSD-3-Clause
License-File: AUTHORS.rst
License-File: LICENSE
Classifier: Development Status :: 4 - Beta
Classifier: Environment :: Web Environment
Classifier: Framework :: Django :: 4.2
Classifier: Framework :: Django :: 5.2
Classifier: Framework :: Django :: 6.0
Classifier: Intended Audience :: Developers
Classifier: License :: OSI Approved :: BSD License
Classifier: Operating System :: OS Independent
Classifier: Programming Language :: Python
Classifier: Programming Language :: Python :: 3
Classifier: Programming Language :: Python :: 3 :: Only
Classifier: Programming Language :: Python :: 3.10
Classifier: Programming Language :: Python :: 3.11
Classifier: Programming Language :: Python :: 3.12
Classifier: Programming Language :: Python :: 3.13
Classifier: Programming Language :: Python :: 3.14
Classifier: Topic :: Software Development :: Libraries
Classifier: Topic :: Utilities
Requires-Python: >=3.10
Requires-Dist: django!=5.0.*,!=5.1.*,>=4.2
Requires-Dist: valkey>=6.0.2
Provides-Extra: brotli
Requires-Dist: brotli>=1.1.0; extra == 'brotli'
Provides-Extra: libvalkey
Requires-Dist: libvalkey>=4.0.1; extra == 'libvalkey'
Provides-Extra: lz4
Requires-Dist: lz4>=4.3.3; extra == 'lz4'
Provides-Extra: msgpack
Requires-Dist: msgpack>=1.1.0; extra == 'msgpack'
Provides-Extra: msgspec
Requires-Dist: msgspec>=0.19.0; extra == 'msgspec'
Provides-Extra: pyzstd
Requires-Dist: backports-zstd>=1.0.0; extra == 'pyzstd'
Provides-Extra: zstd
Requires-Dist: backports-zstd>=1.0.0; extra == 'zstd'
